{
    "X_type": {
        "x1": "Gaussian",
        "x2": "Uniform",
        "x3": "Uniform",
        "x4": "Gaussian",
        "x5": "Gaussian",
        "x6": "Gaussian"
    },
    "Z_type": "Gaussian",
    "max_poly_degree": 4,
    "q_norm": [
        0.75,
        1
    ],
    "Solver": "HybridLAR",
    "save_result_path": "C:/Users/v196m/Desktop/master_project/Masterarbeit/StochasticPCE",
    "SparseOrderTable": [
        [
            0,
            0,
            0,
            0,
            0,
            0,
            0
        ],
        [
            1,
            0,
            0,
            0,
            0,
            0,
            0
        ],
        [
            0,
            0,
            1,
            0,
            0,
            0,
            0
        ],
        [
            0,
            1,
            0,
            0,
            0,
            0,
            0
        ],
        [
            2,
            0,
            0,
            0,
            0,
            0,
            0
        ],
        [
            0,
            1,
            1,
            0,
            0,
            0,
            0
        ],
        [
            1,
            0,
            0,
            0,
            0,
            1,
            0
        ],
        [
            0,
            0,
            0,
            2,
            0,
            0,
            0
        ],
        [
            0,
            0,
            1,
            0,
            2,
            0,
            0
        ],
        [
            0,
            0,
            0,
            1,
            0,
            0,
            0
        ],
        [
            0,
            0,
            0,
            0,
            3,
            0,
            0
        ],
        [
            0,
            2,
            0,
            1,
            0,
            0,
            0
        ],
        [
            0,
            0,
            2,
            0,
            0,
            1,
            0
        ],
        [
            0,
            0,
            0,
            0,
            0,
            1,
            0
        ],
        [
            1,
            2,
            0,
            0,
            0,
            0,
            0
        ],
        [
            0,
            0,
            3,
            0,
            0,
            0,
            0
        ],
        [
            0,
            0,
            0,
            0,
            0,
            0,
            1
        ],
        [
            0,
            1,
            0,
            0,
            0,
            0,
            1
        ],
        [
            0,
            2,
            0,
            0,
            0,
            0,
            1
        ],
        [
            1,
            0,
            0,
            0,
            0,
            0,
            1
        ],
        [
            2,
            0,
            0,
            0,
            0,
            0,
            1
        ],
        [
            0,
            0,
            1,
            0,
            0,
            0,
            1
        ],
        [
            0,
            0,
            2,
            0,
            0,
            0,
            1
        ],
        [
            0,
            0,
            0,
            1,
            0,
            0,
            1
        ],
        [
            0,
            0,
            0,
            2,
            0,
            0,
            1
        ],
        [
            0,
            0,
            0,
            0,
            1,
            0,
            1
        ],
        [
            0,
            0,
            0,
            0,
            2,
            0,
            1
        ],
        [
            0,
            0,
            0,
            0,
            0,
            1,
            1
        ],
        [
            0,
            0,
            0,
            0,
            0,
            2,
            1
        ],
        [
            0,
            0,
            0,
            0,
            0,
            0,
            2
        ],
        [
            0,
            1,
            0,
            0,
            0,
            0,
            2
        ],
        [
            1,
            0,
            0,
            0,
            0,
            0,
            2
        ],
        [
            0,
            0,
            1,
            0,
            0,
            0,
            2
        ],
        [
            0,
            0,
            0,
            1,
            0,
            0,
            2
        ],
        [
            0,
            0,
            0,
            0,
            1,
            0,
            2
        ],
        [
            0,
            0,
            0,
            0,
            0,
            1,
            2
        ],
        [
            0,
            0,
            0,
            0,
            0,
            0,
            3
        ],
        [
            0,
            0,
            0,
            0,
            0,
            0,
            4
        ]
    ],
    "active_list": [
        0,
        5,
        12,
        1,
        8,
        13,
        54,
        29,
        47,
        22,
        49,
        24,
        57,
        51,
        7,
        20
    ],
    "coeffs": [
        -12.168687849725284,
        0.6533440171848939,
        -0.4377618008410666,
        -0.3430551273603859,
        0.2559934176669175,
        0.15218800580918415,
        0.06254197705442988,
        -0.16281111370979606,
        0.07737164265879007,
        -0.13574954143459111,
        0.07910120987425037,
        -0.06580538481326433,
        0.0925891844913463,
        -0.10430286724773226,
        -0.10407813338809051,
        -0.06123881499674792,
        0.1925449947564116,
        -0.1354874536787837,
        -0.06669011658293955,
        0.039571372360379116,
        -0.09438274623900156,
        0.015279327491120756,
        -0.019140724078754803,
        0.008618821163770593,
        0.08428377139867305,
        -0.016839462802796742,
        -0.03060631099032774,
        0.009716454626648916,
        -0.06420045941988423,
        -0.10318363449561765,
        0.0638537073875329,
        -0.016671401914799974,
        0.019661973629056022,
        -0.054389084404750425,
        0.06517176167956285,
        -0.026335692254749084,
        0.016483803058392837,
        0.031956773970348185
    ],
    "p": 4,
    "q": 0.75,
    "Sigma": [
        0.7485389227856719
    ],
    "NfoldMLE_CVs": 47.95295796614882
}